CHANGES.rst
COPYING
MANIFEST.in
Makefile
README.rst
bootstrap-buildout.py
bootstrap-virtualenv.in
bootstrap-virtualenv.py
buildout.cfg
ez_setup.py
requirements-dev.in
requirements-dev.txt
requirements-test.in
requirements.in
requirements.txt
setup.cfg
setup.py
tox.ini
docs/Makefile
docs/changelogs.rst
docs/cli.rst
docs/conf.py
docs/index.rst
docs/intro.rst
docs/make.bat
docs/locale/en/LC_MESSAGES/changelogs.po
docs/locale/en/LC_MESSAGES/cli.po
docs/locale/en/LC_MESSAGES/index.po
docs/locale/en/LC_MESSAGES/intro.po
docs/locale/ko/LC_MESSAGES/changelogs.po
docs/locale/ko/LC_MESSAGES/cli.po
docs/locale/ko/LC_MESSAGES/index.po
docs/locale/ko/LC_MESSAGES/intro.po
docs/locale/pot/changelogs.pot
docs/locale/pot/cli.pot
docs/locale/pot/index.pot
docs/locale/pot/intro.pot
docs/static/empty.css
mete0r.testfixture.egg-info/PKG-INFO
mete0r.testfixture.egg-info/SOURCES.txt
mete0r.testfixture.egg-info/dependency_links.txt
mete0r.testfixture.egg-info/entry_points.txt
mete0r.testfixture.egg-info/not-zip-safe
mete0r.testfixture.egg-info/requires.txt
mete0r.testfixture.egg-info/top_level.txt
mete0r_testfixture/__init__.py
mete0r_testfixture/__main__.py
mete0r_testfixture/cli.py
mete0r_testfixture/testfixture.py
mete0r_testfixture/wsgi.py
mete0r_testfixture/locale/mete0r.testfixture.pot
mete0r_testfixture/locale/en/LC_MESSAGES/mete0r.testfixture.po
mete0r_testfixture/locale/ko/LC_MESSAGES/mete0r.testfixture.po
mete0r_testfixture/recipe/__init__.py
mete0r_testfixture/tests/__init__.py
mete0r_testfixture/tests/fixture_bar.py
mete0r_testfixture/tests/fixture_foo.py
mete0r_testfixture/tests/test_app.py
mete0r_testfixture/tests/test_testfixture.py
virtualenv_support/README.rst