Metadata-Version: 1.1
Name: mete0r.testfixture
Version: 0.0.2
Summary: a testfixture helper
Home-page: https://github.com/mete0r/testfixture
Author: mete0r
Author-email: mete0r@sarangbang.or.kr
License: GNU Affero General Public License v3 or later (AGPLv3+)
Keywords: test fixture
Platform: UNKNOWN
Classifier: Development Status :: 1 - Planning
Classifier: License :: OSI Approved :: GNU Affero General Public License v3 or later (AGPLv3+)
Classifier: Programming Language :: Python :: 2.7
Classifier: Programming Language :: Python :: 3.4
Classifier: Programming Language :: Python :: Implementation :: CPython
Classifier: Programming Language :: Python :: Implementation :: Jython
